endoscopie/.DS_Store
endoscopie/__init__.py
endoscopie/arche.py
endoscopie/commando.py
endoscopie/controller.py
endoscopie/logarithm.py
endoscopie/metadata/endoscopie-meta.json
endoscopie/ssh.py
endoscopie/template_meta.py
endoscopie/templates/openstack-vm-tf.temp
endoscopie/terraform.py
endoscopie/utils.py
endoscopie-0.1.2.dist-info/METADATA
endoscopie-0.1.2.dist-info/WHEEL
endoscopie-0.1.2.dist-info/entry_points.txt
endoscopie-0.1.2.dist-info/RECORD
