Metadata-Version: 2.1
Name: endoscopie
Version: 0.1.2
Summary: 
Author: andrew.chang
Author-email: andrew.chang@kakaoenterprise.com
Requires-Python: >=3.9,<4.0
Classifier: Programming Language :: Python :: 3
Classifier: Programming Language :: Python :: 3.9
Classifier: Programming Language :: Python :: 3.10
Classifier: Programming Language :: Python :: 3.11
Requires-Dist: jinja2 (>=3.1.2,<4.0.0)
Requires-Dist: paramiko (>=3.0.0,<4.0.0)
Requires-Dist: pendulum (>=2.1.2,<3.0.0)
Requires-Dist: pyyaml (>=6.0,<7.0)
Requires-Dist: requests (>=2.28.2,<3.0.0)
Requires-Dist: rich (>=13.3.2,<14.0.0)
Requires-Dist: typer (>=0.7.0,<0.8.0)
